setup.py
./fastdm/__init__.py
fastdm/__init__.py
fastdm/setup.py
fastdm.egg-info/PKG-INFO
fastdm.egg-info/SOURCES.txt
fastdm.egg-info/dependency_links.txt
fastdm.egg-info/top_level.txt