Metadata-Version: 1.0
Name: fastdm
Version: 0.1
Summary: Python wrapper for fast-dm
Home-page: http://www.gillesdehollander.nl
Author: Gilles de Hollander
Author-email: g.dehollander@uva.nl
License: UNKNOWN
Platform: UNKNOWN
